setup.py
bitcoinWebRPC.egg-info/PKG-INFO
bitcoinWebRPC.egg-info/SOURCES.txt
bitcoinWebRPC.egg-info/dependency_links.txt
bitcoinWebRPC.egg-info/not-zip-safe
bitcoinWebRPC.egg-info/top_level.txt
bitcoinwebrpc/__init__.py
bitcoinwebrpc/bitcoin_rpc_examples.py
bitcoinwebrpc/proxy_bitcoin.py
bitcoinwebrpc/webrpc.py