Metadata-Version: 1.0
Name: bitcoinWebRPC
Version: 0.101
Summary: Bitcoin WebRPC for Python
Home-page: https://github.com/benjyz/bitcoinWebRPC
Author: benjyz
Author-email: UNKNOWN
License: MIT
Platform: UNKNOWN
